pdftoword/__init__.py
pdftoword/__main__.py
pdftoword/app.py
pdftoword-0.1.dist-info/METADATA
pdftoword-0.1.dist-info/WHEEL
pdftoword-0.1.dist-info/entry_points.txt
pdftoword-0.1.dist-info/top_level.txt
pdftoword-0.1.dist-info/RECORD
