Metadata-Version: 2.1
Name: pdftoword
Version: 0.1
Summary: A simple PDF to Word converter with a drag-and-drop interface.
Home-page: https://github.com/yourusername/pdftoword
Author: Adam Dinelli
Author-email: isaiahjpeterson007@example.com
Classifier: Programming Language :: Python :: 3
Classifier: License :: OSI Approved :: MIT License
Classifier: Operating System :: OS Independent
Requires-Python: >=3.6
Requires-Dist: tkinterdnd2
Requires-Dist: pdf2docx
